{
  "updated": "2026-03-10 22:28",
  "etfs": {
    "SMH": {
      "ticker": "SMH",
      "name": "반도체 ETF",
      "desc": "VanEck Semiconductor",
      "color": "#3b82f6",
      "currentPrice": 397.33,
      "performance": {
        "1W": 1.6,
        "1M": -1.08,
        "3M": 9.37,
        "YTD": 6.44,
        "12M": 77.07
      }
    },
    "SOXX": {
      "ticker": "SOXX",
      "name": "반도체 ETF",
      "desc": "iShares Semiconductor",
      "color": "#6366f1",
      "currentPrice": 338.81,
      "performance": {
        "1W": 1.2,
        "1M": -2.78,
        "3M": 9.67,
        "YTD": 8.01,
        "12M": 67.38
      }
    },
    "BOTZ": {
      "ticker": "BOTZ",
      "name": "로보틱스 & AI ETF",
      "desc": "Global X Robotics & AI",
      "color": "#10b981",
      "currentPrice": 36.28,
      "performance": {
        "1W": -1.68,
        "1M": -3.2,
        "3M": -0.91,
        "YTD": -1.17,
        "12M": 16.92
      }
    },
    "AIQ": {
      "ticker": "AIQ",
      "name": "AI ETF",
      "desc": "Global X AI & Tech",
      "color": "#f59e0b",
      "currentPrice": 49.67,
      "performance": {
        "1W": 1.76,
        "1M": -0.82,
        "3M": -3.43,
        "YTD": -3.42,
        "12M": 29.44
      }
    },
    "IGV": {
      "ticker": "IGV",
      "name": "소프트웨어 ETF",
      "desc": "iShares Software",
      "color": "#ec4899",
      "currentPrice": 85.65,
      "performance": {
        "1W": 1.82,
        "1M": 3.87,
        "3M": -21.75,
        "YTD": -16.54,
        "12M": -8.32
      }
    },
    "SKYY": {
      "ticker": "SKYY",
      "name": "클라우드 ETF",
      "desc": "First Trust Cloud",
      "color": "#06b6d4",
      "currentPrice": 112.36,
      "performance": {
        "1W": 2.27,
        "1M": -0.28,
        "3M": -15.0,
        "YTD": -12.06,
        "12M": 1.88
      }
    },
    "QQQ": {
      "ticker": "QQQ",
      "name": "나스닥100 ETF",
      "desc": "Invesco QQQ (벤치마크)",
      "color": "#a855f7",
      "currentPrice": 607.77,
      "performance": {
        "1W": 1.03,
        "1M": -0.31,
        "3M": -2.71,
        "YTD": -0.87,
        "12M": 24.21
      }
    },
    "SPY": {
      "ticker": "SPY",
      "name": "S&P500 ETF",
      "desc": "SPDR S&P 500 (벤치마크)",
      "color": "#71717a",
      "currentPrice": 677.18,
      "performance": {
        "1W": -0.46,
        "1M": -1.95,
        "3M": -0.95,
        "YTD": -0.88,
        "12M": 18.96
      }
    }
  }
}