{
  "updated": "2026-05-11 22:26",
  "etfs": {
    "SMH": {
      "ticker": "SMH",
      "name": "반도체 ETF",
      "desc": "VanEck Semiconductor",
      "color": "#3b82f6",
      "currentPrice": 576.31,
      "performance": {
        "1W": 13.72,
        "1M": 31.91,
        "3M": 41.72,
        "YTD": 54.38,
        "12M": 160.47
      }
    },
    "SOXX": {
      "ticker": "SOXX",
      "name": "반도체 ETF",
      "desc": "iShares Semiconductor",
      "color": "#6366f1",
      "currentPrice": 532.76,
      "performance": {
        "1W": 15.3,
        "1M": 37.81,
        "3M": 51.11,
        "YTD": 69.94,
        "12M": 179.63
      }
    },
    "BOTZ": {
      "ticker": "BOTZ",
      "name": "로보틱스 & AI ETF",
      "desc": "Global X Robotics & AI",
      "color": "#10b981",
      "currentPrice": 41.31,
      "performance": {
        "1W": 7.63,
        "1M": 16.6,
        "3M": 8.31,
        "YTD": 12.53,
        "12M": 41.03
      }
    },
    "AIQ": {
      "ticker": "AIQ",
      "name": "AI ETF",
      "desc": "Global X AI & Tech",
      "color": "#f59e0b",
      "currentPrice": 62.85,
      "performance": {
        "1W": 10.05,
        "1M": 27.3,
        "3M": 23.65,
        "YTD": 22.2,
        "12M": 64.39
      }
    },
    "IGV": {
      "ticker": "IGV",
      "name": "소프트웨어 ETF",
      "desc": "iShares Software",
      "color": "#ec4899",
      "currentPrice": 90.69,
      "performance": {
        "1W": 2.54,
        "1M": 21.45,
        "3M": 6.62,
        "YTD": -11.63,
        "12M": -9.68
      }
    },
    "SKYY": {
      "ticker": "SKYY",
      "name": "클라우드 ETF",
      "desc": "First Trust Cloud",
      "color": "#06b6d4",
      "currentPrice": 128.16,
      "performance": {
        "1W": 1.2,
        "1M": 23.04,
        "3M": 11.72,
        "YTD": 0.31,
        "12M": 17.33
      }
    },
    "QQQ": {
      "ticker": "QQQ",
      "name": "나스닥100 ETF",
      "desc": "Invesco QQQ (벤치마크)",
      "color": "#a855f7",
      "currentPrice": 713.29,
      "performance": {
        "1W": 6.01,
        "1M": 16.73,
        "3M": 16.26,
        "YTD": 16.48,
        "12M": 46.79
      }
    },
    "SPY": {
      "ticker": "SPY",
      "name": "S&P500 ETF",
      "desc": "SPDR S&P 500 (벤치마크)",
      "color": "#71717a",
      "currentPrice": 739.3,
      "performance": {
        "1W": 2.97,
        "1M": 8.81,
        "3M": 6.83,
        "YTD": 8.51,
        "12M": 32.34
      }
    }
  }
}