{
  "updated": "2026-06-16 22:40",
  "etfs": {
    "SMH": {
      "ticker": "SMH",
      "name": "반도체 ETF",
      "desc": "VanEck Semiconductor",
      "color": "#3b82f6",
      "currentPrice": 616.0,
      "performance": {
        "1W": 4.23,
        "1M": 10.72,
        "3M": 55.21,
        "YTD": 65.01,
        "12M": 140.44
      }
    },
    "SOXX": {
      "ticker": "SOXX",
      "name": "반도체 ETF",
      "desc": "iShares Semiconductor",
      "color": "#6366f1",
      "currentPrice": 591.24,
      "performance": {
        "1W": 5.23,
        "1M": 16.32,
        "3M": 73.85,
        "YTD": 88.68,
        "12M": 169.42
      }
    },
    "BOTZ": {
      "ticker": "BOTZ",
      "name": "로보틱스 & AI ETF",
      "desc": "Global X Robotics & AI",
      "color": "#10b981",
      "currentPrice": 37.88,
      "performance": {
        "1W": 0.69,
        "1M": -5.84,
        "3M": 7.07,
        "YTD": 3.19,
        "12M": 23.38
      }
    },
    "AIQ": {
      "ticker": "AIQ",
      "name": "AI ETF",
      "desc": "Global X AI & Tech",
      "color": "#f59e0b",
      "currentPrice": 64.64,
      "performance": {
        "1W": 2.34,
        "1M": 5.9,
        "3M": 30.38,
        "YTD": 25.69,
        "12M": 55.7
      }
    },
    "IGV": {
      "ticker": "IGV",
      "name": "소프트웨어 ETF",
      "desc": "iShares Software",
      "color": "#ec4899",
      "currentPrice": 91.37,
      "performance": {
        "1W": -1.68,
        "1M": -0.43,
        "3M": 6.85,
        "YTD": -10.95,
        "12M": -14.0
      }
    },
    "SKYY": {
      "ticker": "SKYY",
      "name": "클라우드 ETF",
      "desc": "First Trust Cloud",
      "color": "#06b6d4",
      "currentPrice": 135.32,
      "performance": {
        "1W": -0.72,
        "1M": 5.31,
        "3M": 19.24,
        "YTD": 5.91,
        "12M": 17.0
      }
    },
    "QQQ": {
      "ticker": "QQQ",
      "name": "나스닥100 ETF",
      "desc": "Invesco QQQ (벤치마크)",
      "color": "#a855f7",
      "currentPrice": 729.86,
      "performance": {
        "1W": 3.11,
        "1M": 2.95,
        "3M": 21.13,
        "YTD": 19.19,
        "12M": 39.17
      }
    },
    "SPY": {
      "ticker": "SPY",
      "name": "S&P500 ETF",
      "desc": "SPDR S&P 500 (벤치마크)",
      "color": "#71717a",
      "currentPrice": 750.33,
      "performance": {
        "1W": 1.8,
        "1M": 1.51,
        "3M": 12.16,
        "YTD": 10.13,
        "12M": 27.12
      }
    }
  }
}