{
  "updated": "2026-04-13 22:42",
  "etfs": {
    "SMH": {
      "ticker": "SMH",
      "name": "반도체 ETF",
      "desc": "VanEck Semiconductor",
      "color": "#3b82f6",
      "currentPrice": 443.34,
      "performance": {
        "1W": 11.96,
        "1M": 14.22,
        "3M": 13.9,
        "YTD": 18.76,
        "12M": 110.94
      }
    },
    "SOXX": {
      "ticker": "SOXX",
      "name": "반도체 ETF",
      "desc": "iShares Semiconductor",
      "color": "#6366f1",
      "currentPrice": 393.34,
      "performance": {
        "1W": 14.31,
        "1M": 19.2,
        "3M": 19.71,
        "YTD": 25.47,
        "12M": 115.58
      }
    },
    "BOTZ": {
      "ticker": "BOTZ",
      "name": "로보틱스 & AI ETF",
      "desc": "Global X Robotics & AI",
      "color": "#10b981",
      "currentPrice": 35.97,
      "performance": {
        "1W": 7.09,
        "1M": 1.07,
        "3M": -5.91,
        "YTD": -2.02,
        "12M": 31.73
      }
    },
    "AIQ": {
      "ticker": "AIQ",
      "name": "AI ETF",
      "desc": "Global X AI & Tech",
      "color": "#f59e0b",
      "currentPrice": 50.58,
      "performance": {
        "1W": 5.93,
        "1M": 4.1,
        "3M": -3.8,
        "YTD": -1.65,
        "12M": 43.41
      }
    },
    "IGV": {
      "ticker": "IGV",
      "name": "소프트웨어 ETF",
      "desc": "iShares Software",
      "color": "#ec4899",
      "currentPrice": 78.7,
      "performance": {
        "1W": -2.19,
        "1M": -7.4,
        "3M": -25.05,
        "YTD": -23.31,
        "12M": -12.06
      }
    },
    "SKYY": {
      "ticker": "SKYY",
      "name": "클라우드 ETF",
      "desc": "First Trust Cloud",
      "color": "#06b6d4",
      "currentPrice": 109.42,
      "performance": {
        "1W": -1.57,
        "1M": -2.06,
        "3M": -15.15,
        "YTD": -14.36,
        "12M": 9.18
      }
    },
    "QQQ": {
      "ticker": "QQQ",
      "name": "나스닥100 ETF",
      "desc": "Invesco QQQ (벤치마크)",
      "color": "#a855f7",
      "currentPrice": 617.39,
      "performance": {
        "1W": 4.91,
        "1M": 3.5,
        "3M": -1.35,
        "YTD": 0.82,
        "12M": 33.13
      }
    },
    "SPY": {
      "ticker": "SPY",
      "name": "S&P500 ETF",
      "desc": "SPDR S&P 500 (벤치마크)",
      "color": "#71717a",
      "currentPrice": 686.1,
      "performance": {
        "1W": 4.12,
        "1M": 3.29,
        "3M": -0.88,
        "YTD": 0.7,
        "12M": 26.49
      }
    }
  }
}